/*
 * Class file version: 52.0
 *
 * Source file: Closeables.java
 */
package de.carne.io;

public final /* super */ class Closeables {
    
    private void <init>() {
        aload_0
        invokespecial
        nop
        aconst_null
        return
        nop
        nop
        nop
        iconst_m1
        nop
        fconst_2
        nop
        nop
        nop
        lconst_1
        nop
        iconst_m1
        nop
        nop
        nop
        lload_1
        nop
        iconst_1
        nop
        lload_3
        nop
        dconst_0
        nop
        nop
        nop
        fconst_1
        nop
        aconst_null
        nop
        nop
        nop
        iconst_2
        nop
        dconst_1
        nop
        bipush
        nop
        nop
    }
    
    public static void close(Object) throws java.io.IOException {
        aload_0
        instanceof
        nop
        iconst_m1
        ifeq
        nop
        fconst_1
        aload_0
        checkcast
        nop
        iconst_m1
        invokeinterface
        nop
        iconst_0
        aconst_null
        nop
        return
        nop
        nop
        nop
        iconst_0
        nop
        fconst_2
        nop
        nop
        nop
        dconst_0
        nop
        iconst_0
        nop
        nop
        nop
        aload_2
        nop
        iconst_4
        nop
        aload_3
        nop
        bipush
        nop
        laload
        nop
        dconst_0
        nop
        nop
        nop
        fconst_1
        nop
        aconst_null
        nop
        nop
        nop
        sipush
        nop
        ldc_w
        nop
        ldc2_w
        nop
        nop
        nop
        iload
        nop
        nop
        nop
        iconst_0
        nop
        aconst_null
        bipush
    }
    
    public static /* varargs */ void closeAll(java.io.Closeable[]) throws java.io.IOException {
        aconst_null
        astore_1
        aload_0
        astore_2
        aload_2
        arraylength
        istore_3
        iconst_0
        istore
        iconst_1
        iload
        iconst_1
        iload_3
        if_icmpge
        nop
        faload
        aload_2
        iload
        iconst_1
        aaload
        astore
        iconst_2
        aload
        iconst_2
        ifnull
        nop
        lload_1
        aload
        iconst_2
        invokeinterface
        nop
        iconst_0
        aconst_null
        nop
        goto
        nop
        iload
        astore
        iconst_3
        aload_1
        ifnonnull
        nop
        lconst_0
        aload
        iconst_3
        astore_1
        goto
        nop
        lconst_0
        aload_1
        aload
        iconst_3
        invokevirtual
        nop
        iconst_2
        iinc
        iconst_1
        aconst_null
        goto
        FF D0
        aload_1
        ifnull
        nop
        iconst_2
        aload_1
        athrow
        return
        nop
        aconst_null
        nop
        iload_1
        nop
        fload_0
        nop
        fload_3
        nop
        iconst_1
        nop
        iconst_0
        nop
        fconst_2
        nop
        nop
        nop
        istore
        nop
        fconst_2
        nop
        nop
        nop
        istore_2
        nop
        iconst_m1
        nop
        lstore_0
        nop
        lload
        nop
        lstore_1
        nop
        iload_1
        nop
        lstore_3
        nop
        fload_0
        nop
        dstore_2
        nop
        fload_3
        nop
        fstore_0
        nop
        dload_1
        nop
        fstore_1
        nop
        aload_1
        nop
        fstore_2
        nop
        daload
        nop
        dstore_0
        nop
        lstore
        nop
        lstore_0
        nop
        istore_2
        nop
        astore_1
        nop
        lstore_2
        nop
        astore_2
        nop
        fstore_0
        nop
        iastore
        nop
        dconst_0
        nop
        nop
        nop
        aload_0
        nop
        iconst_1
        nop
        dload_1
        nop
        bipush
        nop
        iload_1
        nop
        iload_2
        nop
        iconst_3
        nop
        lload
        nop
        lload_3
        nop
        iload_3
        nop
        lload_0
        nop
        iconst_2
        nop
        nop
        nop
        fstore_1
        nop
        lload_1
        nop
        lload_2
        nop
        nop
        nop
        iconst_m1
        nop
        lstore_3
        nop
        lload_3
        nop
        iload_2
        nop
        aconst_null
        nop
        iload
        nop
        nop
        nop
        dstore
        nop
        iconst_3
        FF
        nop
        lconst_1
        nop
        iconst_2
        iconst_4
        nop
        fload_0
        iconst_4
        nop
        fload_1
        iconst_4
        nop
        fload_0
        aconst_null
        aconst_null
        nop
        nop
        FF
        nop
        iload_0
        nop
        iconst_3
        iconst_4
        nop
        fload_0
        iconst_4
        nop
        fload_1
        iconst_4
        nop
        fload_0
        aconst_null
        aconst_null
        iconst_4
        nop
        fload_2
        nop
        aconst_null
        iconst_4
        nop
        fload_1
        FC
        nop
        fconst_0
        iconst_4
        nop
        fload_1
        F9
        nop
        iconst_2
        F8
        nop
        iconst_2
        iconst_2
    }
    
    public static void safeClose(Object) {
        aload_0
        instanceof
        nop
        iconst_m1
        ifeq
        nop
        ldc2_w
        aload_0
        checkcast
        nop
        iconst_m1
        invokeinterface
        nop
        iconst_0
        aconst_null
        nop
        goto
        nop
        iconst_5
        astore_1
        aload_1
        invokestatic
        nop
        iconst_3
        return
        nop
        aconst_null
        nop
        iconst_4
        nop
        bipush
        nop
        ldc_w
        nop
        iconst_1
        nop
        iconst_0
        nop
        fconst_2
        nop
        nop
        nop
        iload_0
        nop
        iconst_3
        nop
        nop
        nop
        dup
        nop
        iconst_4
        nop
        dup_x2
        nop
        bipush
        nop
        dup2_x2
        nop
        ldc_w
        nop
        dup2
        nop
        ldc2_w
        nop
        dup2_x1
        nop
        dload
        nop
        iadd
        nop
        dconst_0
        nop
        nop
        nop
        lload
        nop
        iconst_m1
        nop
        ldc2_w
        nop
        iconst_1
        nop
        iload_1
        nop
        iload_2
        nop
        aconst_null
        nop
        nop
        nop
        aload
        nop
        ldc_w
        nop
        ldc2_w
        nop
        nop
        nop
        iload
        nop
        nop
        nop
        iconst_4
        nop
        iconst_m1
        aastore
        iconst_4
        nop
        fload_1
        iconst_1
    }
    
    public static void safeClose(Throwable, Object) {
        aload_1
        instanceof
        nop
        iconst_m1
        ifeq
        nop
        iload
        aload_1
        checkcast
        nop
        iconst_m1
        invokeinterface
        nop
        iconst_0
        aconst_null
        nop
        goto
        nop
        lconst_0
        astore_2
        aload_0
        aload_2
        invokevirtual
        nop
        iconst_4
        return
        nop
        aconst_null
        nop
        iconst_4
        nop
        bipush
        nop
        ldc_w
        nop
        iconst_1
        nop
        iconst_0
        nop
        fconst_2
        nop
        nop
        nop
        iload_0
        nop
        iconst_3
        nop
        nop
        nop
        idiv
        nop
        iconst_4
        nop
        fdiv
        nop
        bipush
        nop
        lrem
        nop
        ldc_w
        nop
        ddiv
        nop
        ldc2_w
        nop
        irem
        nop
        aload
        nop
        drem
        nop
        dconst_0
        nop
        nop
        nop
        lload_2
        nop
        iconst_0
        nop
        ldc2_w
        nop
        iconst_2
        nop
        iload_1
        nop
        iload_2
        nop
        iconst_m1
        nop
        nop
        nop
        iload_0
        nop
        lload_3
        nop
        dload_1
        nop
        nop
        nop
        nop
        nop
        iload_0
        nop
        ldc_w
        nop
        ldc2_w
        nop
        aconst_null
        nop
        iload
        nop
        nop
        nop
        iconst_4
        nop
        iconst_m1
        aastore
        iconst_4
        nop
        fload_1
        iconst_2
    }

}
