/*
 * Class file version: 52.0
 *
 * Source file: Closeables.java
 */
package de.carne.io;

public final /* super */ class Closeables {
    
    private void <init>() {
        // max_stack: 1
        // max_locals: 1
        0000: aload_0
        0000: invokespecial
        0000: nop
        0000: aconst_null
        0000: return
    }
    
    public static void close(Object) throws java.io.IOException {
        // max_stack: 1
        // max_locals: 1
        0000: aload_0
        0000: instanceof
        0000: nop
        0000: iconst_m1
        0000: ifeq
        0000: nop
        0000: fconst_1
        0000: aload_0
        0000: checkcast
        0000: nop
        0000: iconst_m1
        0000: invokeinterface
        0000: nop
        0000: iconst_0
        0000: aconst_null
        0000: nop
        0000: return
    }
    
    public static /* varargs */ void closeAll(java.io.Closeable[]) throws java.io.IOException {
        // max_stack: 2
        // max_locals: 7
        0000: aconst_null
        0000: astore_1
        0000: aload_0
        0000: astore_2
        0000: aload_2
        0000: arraylength
        0000: istore_3
        0000: iconst_0
        0000: istore
        0000: iconst_1
        0000: iload
        0000: iconst_1
        0000: iload_3
        0000: if_icmpge
        0000: nop
        0000: faload
        0000: aload_2
        0000: iload
        0000: iconst_1
        0000: aaload
        0000: astore
        0000: iconst_2
        0000: aload
        0000: iconst_2
        0000: ifnull
        0000: nop
        0000: lload_1
        0000: aload
        0000: iconst_2
        0000: invokeinterface
        0000: nop
        0000: iconst_0
        0000: aconst_null
        0000: nop
        0000: goto
        0000: nop
        0000: iload
        0000: astore
        0000: iconst_3
        0000: aload_1
        0000: ifnonnull
        0000: nop
        0000: lconst_0
        0000: aload
        0000: iconst_3
        0000: astore_1
        0000: goto
        0000: nop
        0000: lconst_0
        0000: aload_1
        0000: aload
        0000: iconst_3
        0000: invokevirtual
        0000: nop
        0000: iconst_2
        0000: iinc
        0000: iconst_1
        0000: aconst_null
        0000: goto
        0000: FF D0
        0000: aload_1
        0000: ifnull
        0000: nop
        0000: iconst_2
        0000: aload_1
        0000: athrow
        0000: return
    }
    
    public static void safeClose(Object) {
        // max_stack: 1
        // max_locals: 2
        0000: aload_0
        0000: instanceof
        0000: nop
        0000: iconst_m1
        0000: ifeq
        0000: nop
        0000: ldc2_w
        0000: aload_0
        0000: checkcast
        0000: nop
        0000: iconst_m1
        0000: invokeinterface
        0000: nop
        0000: iconst_0
        0000: aconst_null
        0000: nop
        0000: goto
        0000: nop
        0000: iconst_5
        0000: astore_1
        0000: aload_1
        0000: invokestatic
        0000: nop
        0000: iconst_3
        0000: return
    }
    
    public static void safeClose(Throwable, Object) {
        // max_stack: 2
        // max_locals: 3
        0000: aload_1
        0000: instanceof
        0000: nop
        0000: iconst_m1
        0000: ifeq
        0000: nop
        0000: iload
        0000: aload_1
        0000: checkcast
        0000: nop
        0000: iconst_m1
        0000: invokeinterface
        0000: nop
        0000: iconst_0
        0000: aconst_null
        0000: nop
        0000: goto
        0000: nop
        0000: lconst_0
        0000: astore_2
        0000: aload_0
        0000: aload_2
        0000: invokevirtual
        0000: nop
        0000: iconst_4
        0000: return
    }

}
